{
    "bufferViews" : {
        "vertices_id" : {
            "buffer" : "buffer_id",
            "byteLength": 76768,
            "target": 34962,
            "extra" : {
                "Application specific" : "The extra object can contain any properties."
            }
        },
        "indices_id" : {
            "buffer" : "buffer_id",
            "byteLength": 25272,
            "byteOffset": 76768,
            "target": 34963,
            "extra" : {
                "Application specific" : "The extra object can contain any properties."
            }
        }        
    }
}